dynamsoftservice/__init__.py
twain_wia_sane_scanner-2.0.2.dist-info/licenses/LICENSE
twain_wia_sane_scanner-2.0.2.dist-info/METADATA
twain_wia_sane_scanner-2.0.2.dist-info/WHEEL
twain_wia_sane_scanner-2.0.2.dist-info/top_level.txt
twain_wia_sane_scanner-2.0.2.dist-info/RECORD
